wrench/__init__.py
wrench/commands.py
wrench/config.py
wrench/context.py
wrench/exceptions.py
wrench/io.py
wrench/models.py
wrench/passbolt_api.py
wrench/passbolt_shell.py
wrench/resources.py
wrench/services.py
wrench/users.py
wrench/utils.py
wrench/validators.py
wrench/translators/__init__.py
wrench/translators/foreign.py
wrench/translators/local.py
passbolt_wrench-0.4.2.dist-info/AUTHORS
passbolt_wrench-0.4.2.dist-info/LICENSE
passbolt_wrench-0.4.2.dist-info/METADATA
passbolt_wrench-0.4.2.dist-info/WHEEL
passbolt_wrench-0.4.2.dist-info/entry_points.txt
passbolt_wrench-0.4.2.dist-info/top_level.txt
passbolt_wrench-0.4.2.dist-info/RECORD
