Metadata-Version: 2.1
Name: passbolt-wrench
Version: 0.4.2
Summary: wrench is a CLI for Passbolt
Home-page: https://github.com/liip/wrench
Author: The wrench developers
Author-email: wrench@liip.ch
License: GPLv3+
Platform: UNKNOWN
Classifier: Environment :: Console
Classifier: Development Status :: 5 - Production/Stable
Classifier: Programming Language :: Python :: 3.5
Classifier: Programming Language :: Python :: 3.6
Requires-Dist: click (>=6.0)
Requires-Dist: requests
Requires-Dist: requests-gpgauthlib (>=0.1.0)
